{"cameraMode":{"drawMode":0,"name":"Shaded","section":"Shading Mode"},"sceneLighting":false,"audioPlay":false,"sceneViewState":{"m_AlwaysRefresh":false,"showFog":true,"showSkybox":false,"showFlares":true,"showImageEffects":true,"showParticleSystems":true,"showVisualEffectGraphs":true,"m_FxEnabled":true},"in2DMode":false,"pivot":{"x":2.578507423400879,"y":1.098779320716858,"z":2.4738552570343019},"rotation":{"x":-0.00922820158302784,"y":0.9893944263458252,"z":0.0728517547249794,"w":0.12532761693000794},"size":1.2062177658081055,"orthographic":false}